<Language Name="English" IsDefault="false" IsRightToLeft="false">
  
  <LocaleResource Name="Plugins.FriendlyName.SmartStore.IPayment" AppendRootKey="false">
    <Value>1 &amp; 1 ipayment Payment Methods</Value>
  </LocaleResource>
  <LocaleResource Name="Plugins.Description.SmartStore.IPayment" AppendRootKey="false">
    <Value>Provides the 1 &amp; 1 ipayment payment methods for credit card and direct debit.</Value>
  </LocaleResource>
  
	<LocaleResource Name="Plugins.FriendlyName.Payments.IPaymentCreditCard" AppendRootKey="false">
		<Value>ipayment credit card</Value>
	</LocaleResource>
  <LocaleResource Name="Plugins.FriendlyName.Payments.IPaymentDirectDebit" AppendRootKey="false">
    <Value>ipayment direct debit</Value>
  </LocaleResource>

  <LocaleResource Name="Plugins.Payments.IPaymentCreditCard" AppendRootKey="false">
    <Children>
	    <LocaleResource Name="AdminInstruction">
		    <Value>
          <![CDATA[<p>Steps to configure ipayment:</p>
<ol>
<li>Log into <a href="https://admin.ipayment.de/" target="_blank">your ipayment account</a>.</li>
<li>The overview shows you the data account ID, application ID, application password and transaction password. Enter them below on this page.</li>
<li>Click <b>applications</b>, select your application\store and click <b>edit</b>.</li>
<li>There please note the following settings and don't forget to save:
<ul>
<li>Deactivate <b>force to enter address</b></li>
<li>Leave <b>hidden trigger url</b> empty (transmitted by store)</li>
<li>Enter any <b>transaction security key</b> and enter it below on this page too</li>
<li>Deactivate <b>address checking</b></li>
</ul>
</li>
</ol>
<p>The store must be accessible through one of the default ports 80 or 443 for iPayment feedback.</p>]]>
		    </Value>
	    </LocaleResource>
	    <LocaleResource Name="AccountID">
		    <Value>Account ID</Value>
	    </LocaleResource>
	    <LocaleResource Name="AccountID.Hint">
		    <Value>Your ipayment account ID.</Value>
	    </LocaleResource>
	    <LocaleResource Name="AppID">
		    <Value>Application ID</Value>
	    </LocaleResource>
	    <LocaleResource Name="AppID.Hint">
		    <Value>Your ipayment Application ID.</Value>
	    </LocaleResource>
	    <LocaleResource Name="AppPassword">
		    <Value>Application password</Value>
	    </LocaleResource>
	    <LocaleResource Name="AppPassword.Hint">
		    <Value>Your ipayment application password.</Value>
	    </LocaleResource>
	    <LocaleResource Name="AdminActionPassword">
		    <Value>Action password</Value>
	    </LocaleResource>
	    <LocaleResource Name="AdminActionPassword.Hint">
		    <Value>Your ipayment action password.</Value>
	    </LocaleResource>
	    <LocaleResource Name="SecurityKey">
		    <Value>Transaction security key</Value>
	    </LocaleResource>
	    <LocaleResource Name="SecurityKey.Hint">
		    <Value>Your ipayment transaction security key. Security mechanism to prevent manipulation of transfered data.</Value>
	    </LocaleResource>
	    <LocaleResource Name="TransactionType">
		    <Value>Transaction type</Value>
	    </LocaleResource>
	    <LocaleResource Name="TransactionType.Hint">
		    <Value>Transaction type.</Value>
	    </LocaleResource>
	    <LocaleResource Name="AdditionalFee">
		    <Value>Additional fee</Value>
	    </LocaleResource>
	    <LocaleResource Name="AdditionalFee.Hint">
		    <Value>Enter additional fee to charge your customers.</Value>
	    </LocaleResource>
	    <LocaleResource Name="AdditionalFeePercentage">
		    <Value>Additional fee. Use percentage</Value>
	    </LocaleResource>
	    <LocaleResource Name="AdditionalFeePercentage.Hint">
		    <Value>Determines whether to apply a percentage additional fee to the order total. If not enabled, a fixed value is used.</Value>
	    </LocaleResource>
	    <LocaleResource Name="CheckIP">
		    <Value>Check IP address</Value>
	    </LocaleResource>
	    <LocaleResource Name="CheckIP.Hint">
		    <Value>Security mechanism to ensure that responses are always from the ipayment server.</Value>
	    </LocaleResource>
	    <LocaleResource Name="CheckCcMismatch">
		    <Value>Check card number</Value>
	    </LocaleResource>
	    <LocaleResource Name="CheckCcMismatch.Hint">
		    <Value>Check the box if ipayment should check if there is a mismatch of credit card number and card type.</Value>
	    </LocaleResource>
	    <LocaleResource Name="StartDate">
		    <Value>Start date</Value>
	    </LocaleResource>
	    <LocaleResource Name="StartDate.Hint">
		    <Value>Start date of your credit card. Only required for british Maestro or Solo cards.</Value>
	    </LocaleResource>
	    <LocaleResource Name="IssueNumber">
		    <Value>Issue number</Value>
	    </LocaleResource>
	    <LocaleResource Name="IssueNumber.Hint">
		    <Value>Issue number of your credit card. Only required for british Maestro or Solo cards.</Value>
	    </LocaleResource>
	    <LocaleResource Name="ModeAuthAndCapture">
		    <Value>Immediately debit</Value>
	    </LocaleResource>
	    <LocaleResource Name="ModeAuth">
		    <Value>Authorize immediately, debit later</Value>
	    </LocaleResource>
	    <LocaleResource Name="InvalidCredentials">
		    <Value>Incomplete credentials for ipayment. Please enter the required data in the configuration area of the plugin.</Value>
	    </LocaleResource>
	    <LocaleResource Name="PaymentStartFailed">
		    <Value>ipayment payment cannot be initiated.</Value>
	    </LocaleResource>
	    <LocaleResource Name="NotificationError">
		    <Value>Error during processing of an ipayment notification.</Value>
	    </LocaleResource>
	    <LocaleResource Name="IpaymentNotificationError">
		    <Value>{0} (fatal: {1}, code: {2}, detail: {3}).</Value>
	    </LocaleResource>
	    <LocaleResource Name="UnknownError">
		    <Value>Unknown ipayment error.</Value>
	    </LocaleResource>
	    <LocaleResource Name="InvalidIP">
		    <Value>Received ipayment notification from invalid IP ad´dress ({0}).</Value>
	    </LocaleResource>
	    <LocaleResource Name="NoCacheData">
		    <Value>No cache data for ipayment notification with order GUID {0} found.</Value>
	    </LocaleResource>
	    <LocaleResource Name="NoOrderGuid">
		    <Value>Order GUID for ipayment notification missing. Not able to find the  order.</Value>
	    </LocaleResource>
	    <LocaleResource Name="PaymentAlreadyRunning">
		    <Value>A payment process for your order is already running at this moment. Please try again later.</Value>
	    </LocaleResource>
	    <LocaleResource Name="ExcludedCreditCards">
		    <Value>Excluded credit cards</Value>
	    </LocaleResource>
	    <LocaleResource Name="ExcludedCreditCards.Hint">
		    <Value>Credit cards that customers may not pay with.</Value>
	    </LocaleResource>

    </Children>
  </LocaleResource>
  
  <LocaleResource Name="Plugins.Payments.IPaymentDirectDebit" AppendRootKey="false">
    <Children>
      <LocaleResource Name="AdminInstruction">
        <Value>
          <![CDATA[<p>Steps to configure ipayment:</p><ol>
<li>Log into <a href="https://admin.ipayment.de/" target="_blank">your ipayment account</a>.</li>
<li>The overview shows you the data account ID, application ID, application password and transaction password. Enter them below on this page.</li>
<li>Click <b>applications</b>, select your application\store and click <b>edit</b>.</li>
<li>There please note the following settings and don't forget to save:
<ul>
<li>Deactivate <b>force to enter address</b></li>
<li>Leave <b>hidden trigger url</b> empty (transmitted by store)</li>
<li>Enter any <b>transaction security key</b> and enter it below on this page too</li>
<li>Deactivate <b>address checking</b></li>
</ul>
</li>
</ol>
<p>The store must be accessible through one of the default ports 80 or 443 for iPayment feedback.</p>]]>
        </Value>
      </LocaleResource>
      <LocaleResource Name="AccountID">
        <Value>Account ID</Value>
      </LocaleResource>
      <LocaleResource Name="AccountID.Hint">
        <Value>Your ipayment account ID.</Value>
      </LocaleResource>
      <LocaleResource Name="AppID">
        <Value>Application ID</Value>
      </LocaleResource>
      <LocaleResource Name="AppID.Hint">
        <Value>Your ipayment Application ID.</Value>
      </LocaleResource>
      <LocaleResource Name="AppPassword">
        <Value>Application password</Value>
      </LocaleResource>
      <LocaleResource Name="AppPassword.Hint">
        <Value>Your ipayment application password.</Value>
      </LocaleResource>
      <LocaleResource Name="AdminActionPassword">
        <Value>Admin action password</Value>
      </LocaleResource>
      <LocaleResource Name="AdminActionPassword.Hint">
        <Value>Your ipayment admin action password.</Value>
      </LocaleResource>
      <LocaleResource Name="SecurityKey">
        <Value>Security key</Value>
      </LocaleResource>
      <LocaleResource Name="SecurityKey.Hint">
        <Value>Your ipayment security key. Security mechanism to prevent manipulation of transfered data.</Value>
      </LocaleResource>
      <LocaleResource Name="TransactionType">
        <Value>Transaction type</Value>
      </LocaleResource>
      <LocaleResource Name="TransactionType.Hint">
        <Value>Transaction type.</Value>
      </LocaleResource>
      <LocaleResource Name="AdditionalFee">
        <Value>Additional fee</Value>
      </LocaleResource>
      <LocaleResource Name="AdditionalFee.Hint">
        <Value>Enter additional fee to charge your customers.</Value>
      </LocaleResource>
      <LocaleResource Name="AdditionalFeePercentage">
        <Value>Additinoal fee. Use percentage</Value>
      </LocaleResource>
      <LocaleResource Name="AdditionalFeePercentage.Hint">
        <Value>Determines whether to apply a percentage additional fee to the order total. If not enabled, a fixed value is used.</Value>
      </LocaleResource>
      <LocaleResource Name="CheckIP">
        <Value>Check IP address</Value>
      </LocaleResource>
      <LocaleResource Name="CheckIP.Hint">
        <Value>Security mechanism to ensure that responses are always from the ipayment server.</Value>
      </LocaleResource>
      <LocaleResource Name="ElvAccountHolder">
        <Value>Account holder name</Value>
      </LocaleResource>
      <LocaleResource Name="ElvAccountHolder.Hint">
        <Value>Holder name of the bank account</Value>
      </LocaleResource>
      <LocaleResource Name="ElvAccountNumber">
        <Value>Account number</Value>
      </LocaleResource>
      <LocaleResource Name="ElvAccountNumber.Hint">
        <Value>Account number</Value>
      </LocaleResource>
      <LocaleResource Name="ElvBankCode">
        <Value>Bank code</Value>
      </LocaleResource>
      <LocaleResource Name="ElvBankCode.Hint">
        <Value>Bank code number</Value>
      </LocaleResource>
      <LocaleResource Name="ElvCountry">
        <Value>Country</Value>
      </LocaleResource>
      <LocaleResource Name="ElvCountry.Hint">
        <Value>Country of your bank account.</Value>
      </LocaleResource>
      <LocaleResource Name="ElvBankName">
        <Value>Bank name</Value>
      </LocaleResource>
      <LocaleResource Name="ElvBankName.Hint">
        <Value>Name of your bank.</Value>
      </LocaleResource>
      <LocaleResource Name="ElvIBAN">
        <Value>IBAN</Value>
      </LocaleResource>
      <LocaleResource Name="ElvIBAN.Hint">
        <Value>International Bank Account Number</Value>
      </LocaleResource>
      <LocaleResource Name="ElvBIC">
        <Value>BIC</Value>
      </LocaleResource>
      <LocaleResource Name="ElvBIC.Hint">
        <Value>Bank Interchange Code</Value>
      </LocaleResource>
      <LocaleResource Name="ModeAuthAndCapture">
        <Value>Immediately debit</Value>
      </LocaleResource>
      <LocaleResource Name="ModeAuth">
        <Value>Authorize immediately, debit later</Value>
      </LocaleResource>
      <LocaleResource Name="InvalidCredentials">
        <Value>Incomplete credentials for ipayment. Please enter the required data in the configuration area.</Value>
      </LocaleResource>
      <LocaleResource Name="PaymentStartFailed">
        <Value>ipayment payment cannot be initiated.</Value>
      </LocaleResource>
      <LocaleResource Name="NotificationError">
        <Value>Error during processing of an ipayment notification.</Value>
      </LocaleResource>
      <LocaleResource Name="IpaymentNotificationError">
        <Value>{0} (fatal: {1}, code: {2}, detail: {3}).</Value>
      </LocaleResource>
      <LocaleResource Name="UnknownError">
        <Value>Unknown ipayment error.</Value>
      </LocaleResource>
      <LocaleResource Name="InvalidIP">
        <Value>Received ipayment notification from invalid IP adress ({0}).</Value>
      </LocaleResource>
      <LocaleResource Name="NoCacheData">
        <Value>No cache data for ipayment notification with order GUID {0} found.</Value>
      </LocaleResource>
      <LocaleResource Name="NoOrderGuid">
        <Value>Order GUID for ipayment notification missing. Not able to find the  order.</Value>
      </LocaleResource>
      <LocaleResource Name="PaymentAlreadyRunning">
        <Value>A payment process for your order is already running at this moment. Please try again later.</Value>
      </LocaleResource>
      <LocaleResource Name="EnterIBAN">
        <Value>Enter IBAN</Value>
      </LocaleResource>
      <LocaleResource Name="NoEnterIBAN">
        <Value>No</Value>
      </LocaleResource>
      <LocaleResource Name="YesEnterIBAN">
        <Value>Yes</Value>
      </LocaleResource>
      <LocaleResource Name="ElvAccountHolderRequired">
        <Value>Please enter the name of the account holder.</Value>
      </LocaleResource>
      <LocaleResource Name="ElvAccountNumberRequired">
        <Value>Please enter your account number.</Value>
      </LocaleResource>
      <LocaleResource Name="ElvBankCodeRequired">
        <Value>Please enter the bank code.</Value>
      </LocaleResource>
      <LocaleResource Name="ElvIBANRequired">
        <Value>Please enter the IBAN (International Bank Account Number).</Value>
      </LocaleResource>
      <LocaleResource Name="ElvBICRequired">
        <Value>Please enter the BIC (Bank Interchange Code).</Value>
      </LocaleResource>
    </Children>
  </LocaleResource>
</Language>